src/__init__.py
src/data/__init__.py
src/data/wrapper_bin.js
semantic_locators.py
semantic_locators-2.1.0.dist-info/WHEEL
semantic_locators-2.1.0.dist-info/METADATA
semantic_locators-2.1.0.dist-info/RECORD
