Metadata-Version: 2.1
Name: semantic-locators
Version: 2.1.0
Summary: Semantic Locators are a human readable, resilient and accessibility-enforcing way to find web elements. This package adds semantic locator support to webdriver
Home-page: https://github.com/google/semantic-locators
License: Apache-2.0
Author: Alex Lloyd
Author-email: alexlloyd@google.com
Requires-Python: >=3.6,<3.10
Classifier: Development Status :: 5 - Production/Stable
Classifier: Intended Audience :: Developers
Classifier: License :: OSI Approved :: Apache Software License
Classifier: Operating System :: OS Independent
Classifier: Programming Language :: Python :: 3
Classifier: Programming Language :: Python :: 3.6
Classifier: Programming Language :: Python :: 3.7
Classifier: Programming Language :: Python :: 3.8
Classifier: Programming Language :: Python :: 3.9
Classifier: Topic :: Software Development :: Testing
Requires-Dist: importlib-resources (>=5.1.2,<6.0.0)
Requires-Dist: selenium (>=3.141.0,<4.0.0)
Project-URL: Repository, https://github.com/google/semantic-locators
